docs/autogen_config.py
docs/source/conf.py
jupyterlab_server/__init__.py
jupyterlab_server/__main__.py
jupyterlab_server/_version.py
jupyterlab_server/app.py
jupyterlab_server/config.py
jupyterlab_server/handlers.py
jupyterlab_server/licenses_app.py
jupyterlab_server/licenses_handler.py
jupyterlab_server/listings_handler.py
jupyterlab_server/process.py
jupyterlab_server/process_app.py
jupyterlab_server/pytest_plugin.py
jupyterlab_server/server.py
jupyterlab_server/settings_handler.py
jupyterlab_server/settings_utils.py
jupyterlab_server/spec.py
jupyterlab_server/themes_handler.py
jupyterlab_server/translation_utils.py
jupyterlab_server/translations_handler.py
jupyterlab_server/workspaces_app.py
jupyterlab_server/workspaces_handler.py
elixirlab_server-2.16.6.dist-info/METADATA
elixirlab_server-2.16.6.dist-info/WHEEL
elixirlab_server-2.16.6.dist-info/licenses/LICENSE
elixirlab_server-2.16.6.dist-info/RECORD
