Metadata-Version: 2.1
Name: elixirlab_server
Version: 2.16.6
Summary: A set of server components for ElixirLab and ElixirLab like applications.
Author-email: ciusji <bqjimaster@gmail.com>
License: Copyright (c) 2015-2017, Project Jupyter Contributors
License-File: LICENSE
Keywords: elixir,jupyter,jupyterlab
Classifier: Framework :: Jupyter
Classifier: Framework :: Jupyter :: JupyterLab
Classifier: Intended Audience :: Developers
Classifier: Intended Audience :: Science/Research
Classifier: Intended Audience :: System Administrators
Classifier: License :: OSI Approved :: BSD License
Classifier: Programming Language :: Python
Classifier: Programming Language :: Python :: 3 :: Only
Classifier: Programming Language :: Python :: 3.7
Classifier: Programming Language :: Python :: 3.8
Classifier: Programming Language :: Python :: 3.9
Classifier: Programming Language :: Python :: 3.10
Classifier: Programming Language :: Python :: 3.11
Classifier: Typing :: Typed
Requires-Python: >=3.7
Requires-Dist: babel>=2.10
Requires-Dist: elixir-server>=2.1.0.dev204
Requires-Dist: importlib-metadata>=4.8.3; python_version < '3.10'
Requires-Dist: jinja2>=3.0.3
Requires-Dist: json5>=0.9.0
Requires-Dist: jsonschema>=3.0.1
Requires-Dist: packaging>=21.3
Requires-Dist: requests>=2.28
Provides-Extra: docs
Requires-Dist: autodoc-traits; extra == 'docs'
Requires-Dist: docutils<0.20; extra == 'docs'
Requires-Dist: jinja2<3.2.0; extra == 'docs'
Requires-Dist: mistune<3; extra == 'docs'
Requires-Dist: myst-parser; extra == 'docs'
Requires-Dist: pydata-sphinx-theme; extra == 'docs'
Requires-Dist: sphinx; extra == 'docs'
Requires-Dist: sphinx-copybutton; extra == 'docs'
Requires-Dist: sphinxcontrib-openapi; extra == 'docs'
Provides-Extra: lint
Requires-Dist: black[jupyter]>=22.6.0; extra == 'lint'
Requires-Dist: mdformat-gfm>=0.3.5; extra == 'lint'
Requires-Dist: mdformat>0.7; extra == 'lint'
Requires-Dist: ruff>=0.0.156; extra == 'lint'
Provides-Extra: openapi
Requires-Dist: openapi-core>=0.14.2; extra == 'openapi'
Requires-Dist: ruamel-yaml; extra == 'openapi'
Provides-Extra: test
Requires-Dist: codecov; extra == 'test'
Requires-Dist: ipykernel; extra == 'test'
Requires-Dist: openapi-core~=0.14.2; extra == 'test'
Requires-Dist: openapi-spec-validator<0.6; extra == 'test'
Requires-Dist: pytest-console-scripts; extra == 'test'
Requires-Dist: pytest-cov; extra == 'test'
Requires-Dist: pytest-jupyter[server]>=0.6; extra == 'test'
Requires-Dist: pytest-timeout; extra == 'test'
Requires-Dist: pytest>=7.0; extra == 'test'
Requires-Dist: requests-mock; extra == 'test'
Requires-Dist: ruamel-yaml; extra == 'test'
Requires-Dist: strict-rfc3339; extra == 'test'
Provides-Extra: typing
Requires-Dist: mypy>=0.990; extra == 'typing'
